feeds/__init__.py
feeds/cache.py
feeds/cli.py
feeds/default_settings.py
feeds/downloadermiddlewares.py
feeds/exceptions.py
feeds/exporters.py
feeds/items.py
feeds/loaders.py
feeds/pipelines.py
feeds/settings.py
feeds/spidermiddlewares.py
feeds/utils.py
feeds/spiders/__init__.py
feeds/spiders/arstechnica_com.py
feeds/spiders/atv_at.py
feeds/spiders/biblioweb_at.py
feeds/spiders/cbird_at.py
feeds/spiders/derstandard_at.py
feeds/spiders/economist_com.py
feeds/spiders/falter_at.py
feeds/spiders/ft_com.py
feeds/spiders/gem2go.py
feeds/spiders/generic.py
feeds/spiders/indiehackers_com.py
feeds/spiders/konsument_at.py
feeds/spiders/kurier_at.py
feeds/spiders/lbg_at.py
feeds/spiders/lwn_net.py
feeds/spiders/momoxfashion_com.py
feeds/spiders/nachrichten_at.py
feeds/spiders/npr_org.py
feeds/spiders/oe1_orf_at.py
feeds/spiders/orf_at.py
feeds/spiders/profil_at.py
feeds/spiders/puls4_com.py
feeds/spiders/python_patterns_guide.py
feeds/spiders/servustv_com.py
feeds/spiders/spotify_com.py
feeds/spiders/theoatmeal_com.py
feeds/spiders/trend_at.py
feeds/spiders/tuwien_ac_at.py
feeds/spiders/tvthek_orf_at.py
feeds/spiders/uebermedien_de.py
feeds/spiders/usenix_org.py
feeds/spiders/verbraucherrecht_at.py
feeds/spiders/vice_com.py
feeds/spiders/wienerlinien_at.py
feeds/spiders/wienerzeitung_at.py
feeds/spiders/zeitdiebin_at.py
PyFeeds-2024.5.1.dist-info/LICENSE
PyFeeds-2024.5.1.dist-info/METADATA
PyFeeds-2024.5.1.dist-info/WHEEL
PyFeeds-2024.5.1.dist-info/entry_points.txt
PyFeeds-2024.5.1.dist-info/top_level.txt
PyFeeds-2024.5.1.dist-info/RECORD
