Metadata-Version: 2.1
Name: PyFeeds
Version: 2024.5.1
Summary: DIY Atom feeds in times of social media and paywalls
Home-page: https://github.com/PyFeeds/PyFeeds
Author: Florian Preinstorfer, Lukas Anzinger
Author-email: florian@nblock.org, lukas@lukasanzinger.at
Classifier: Development Status :: 4 - Beta
Classifier: Environment :: Console
Classifier: Framework :: Scrapy
Classifier: Intended Audience :: Developers
Classifier: License :: OSI Approved :: GNU Affero General Public License v3
Classifier: Programming Language :: Python :: 3
Classifier: Programming Language :: Python :: 3.8
Classifier: Programming Language :: Python :: 3.9
Classifier: Programming Language :: Python :: 3.10
Classifier: Programming Language :: Python :: 3.11
Classifier: Programming Language :: Python :: 3.12
Classifier: Topic :: Internet :: WWW/HTTP
License-File: LICENSE
Requires-Dist: click
Requires-Dist: dateparser
Requires-Dist: feedparser
Requires-Dist: itemloaders
Requires-Dist: lxml[html_clean]
Requires-Dist: python-dateutil
Requires-Dist: pyxdg
Requires-Dist: readability-lxml
Requires-Dist: scrapy
Requires-Dist: scrapy-inline-requests
Provides-Extra: docs
Requires-Dist: sphinx ; extra == 'docs'
Requires-Dist: sphinx-rtd-theme ; extra == 'docs'
Provides-Extra: test
Requires-Dist: pytest ; extra == 'test'
